tests/__init__.py
tests/dbops/__init__.py
tests/dbops/mysql_op.py
tests/dispatch/__init__.py
tests/dispatch/config/__init__.py
tests/dispatch/config/celery_local_config.py
tests/dispatch/rules/__init__.py
tests/dispatch/rules/rule_temp.py
tests/dispatch/test_dispatch.py
tests/helpers/__init__.py
tests/helpers/test_mysql_helper.py
tests/helpers/test_pika_helper.py
tests/helpers/test_redis_helper.py
tests/server_center/check_upload_file.py
tests/test_dispatch/__init__.py
tests/test_dispatch/config/__init__.py
tests/test_dispatch/config/celery_config.py
tests/test_dispatch/main.py
tests/test_dispatch/rules/__init__.py
tests/test_dispatch/rules/export.py
tests/test_dispatch/task_register.py
tests/test_ip2region.py
tests/test_submit/__init__.py
tests/test_submit/schedule_rule/__init__.py
tests/test_submit/schedule_rule/schedule_tests/__init__.py
tests/test_submit/schedule_rule/schedule_tests/schedule_test_statistic_flow.py
tests/test_submit/schedule_rule/schedule_tests/schedule_test_statistic_multi_flow.py
tests/test_submit/schedule_rule/schedule_tests/schedule_test_statistic_task.py
tests/test_submit/test_submit.json
tests/test_submit/test_submit.py
tests/test_xlogging.py
tests/test_xtrace.py
tests/utils/__init__.py
tests/xcelery/__init__.py
tests/xcelery/config/__init__.py
tests/xcelery/config/celery_local_config.py
tests/xcelery/task_register.py
tests/xcelery/test_celery.py
yyxx_game_pkg/__init__.py
yyxx_game_pkg/async_dbops/__init__.py
yyxx_game_pkg/async_dbops/async_das_ch_op.py
yyxx_game_pkg/async_dbops/async_das_client.py
yyxx_game_pkg/async_dbops/async_das_doris_op.py
yyxx_game_pkg/async_dbops/async_das_es_op.py
yyxx_game_pkg/async_dbops/async_sqlalchemy_op.py
yyxx_game_pkg/async_dbops/base.py
yyxx_game_pkg/center_api/__init__.py
yyxx_game_pkg/center_api/core/__init__.py
yyxx_game_pkg/center_api/core/ex_logger.py
yyxx_game_pkg/center_api/model/Operator.py
yyxx_game_pkg/center_api/model/OperatorServer.py
yyxx_game_pkg/center_api/model/RechargeConfig.py
yyxx_game_pkg-2025.3.4.1.dist-info/METADATA
yyxx_game_pkg-2025.3.4.1.dist-info/WHEEL
yyxx_game_pkg-2025.3.4.1.dist-info/RECORD
