Metadata-Version: 2.3
Name: yyxx-game-pkg
Version: 2025.3.4.1
Summary: yyxx game custom module
License: MIT
Author: yyxx-game
Requires-Python: >=3.9,<4
Classifier: License :: OSI Approved :: MIT License
Classifier: Operating System :: OS Independent
Classifier: Programming Language :: Python :: 3
Classifier: Programming Language :: Python :: 3.9
Classifier: Programming Language :: Python :: 3.10
Classifier: Programming Language :: Python :: 3.11
Classifier: Programming Language :: Python :: 3.12
Classifier: Programming Language :: Python :: 3.13
Provides-Extra: center-api
Provides-Extra: server-center
Provides-Extra: stat
Requires-Dist: aiomysql (==0.2.0) ; extra == "stat"
Requires-Dist: celery (==5.2.7)
Requires-Dist: cookiecutter (>=2.1.1,<3.0.0) ; extra == "center-api"
Requires-Dist: dbutils (>=3.0.2,<4.0.0)
Requires-Dist: django (>=4.2.1,<5.0.0) ; extra == "server-center"
Requires-Dist: elasticsearch (==8.14.0) ; extra == "stat"
Requires-Dist: fastapi (>=0.94.0,<0.95.0) ; extra == "stat"
Requires-Dist: filetype (>=1.2.0,<2.0.0) ; extra == "server-center"
Requires-Dist: flask (>=2.3.2,<3.0.0) ; extra == "center-api"
Requires-Dist: httpx (>=0.24.1,<0.25.0)
Requires-Dist: line-profiler (>=4.0.3,<5.0.0)
Requires-Dist: opentelemetry-api (>=1.16.0,<2.0.0)
Requires-Dist: opentelemetry-exporter-jaeger (>=1.16.0,<2.0.0)
Requires-Dist: opentelemetry-instrumentation-celery (==0.37b0)
Requires-Dist: opentelemetry-instrumentation-django (>=0.37b0,<0.38)
Requires-Dist: opentelemetry-instrumentation-fastapi (==0.37b.0)
Requires-Dist: opentelemetry-instrumentation-flask (>=0.37b0,<0.38)
Requires-Dist: opentelemetry-instrumentation-requests (>=0.37b0,<0.38)
Requires-Dist: opentelemetry-sdk (>=1.16.0,<2.0.0)
Requires-Dist: pandas (>=1.5.3,<2.0.0)
Requires-Dist: pika (>=1.3.1,<2.0.0)
Requires-Dist: pillow (>=9.5.0,<10.0.0) ; extra == "server-center"
Requires-Dist: pycryptodome (>=3.17,<4.0)
Requires-Dist: pymongo (==3.13.0)
Requires-Dist: pymysql (>=1.0.2,<2.0.0)
Requires-Dist: pyparsing (>=3.1.0,<4.0.0)
Requires-Dist: redis (>=4.5.1,<5.0.0)
Requires-Dist: requests (>=2.32.3,<3.0.0) ; extra == "stat"
Requires-Dist: scipy (>=1.12.0,<2.0.0) ; extra == "stat"
Requires-Dist: sqlalchemy (==1.4.54) ; extra == "stat"
Requires-Dist: toml (>=0.10.2,<0.11.0)
Requires-Dist: ujson (>=5.7.0,<6.0.0)
Requires-Dist: uvicorn (>=0.21.0,<0.22.0)
Project-URL: Homepage, https://github.com/yyxxgame/yyxxgame-pkg
Project-URL: Repository, https://github.com/yyxxgame/yyxxgame-pkg
